agentdock/__init__.py
agentdock/cli.py
agentdock/agents/base.py
agentdock/agents/runner.py
agentdock/agents/simple_openai_agent.py
agentdock/core/__init__.py
agentdock/core/base_protocol.py
agentdock/core/base_protocol_adapter.py
agentdock/core/client.py
agentdock/core/connector.py
agentdock/core/network.py
agentdock/core/system_commands.py
agentdock/launchers/__init__.py
agentdock/launchers/discovery_connector.py
agentdock/launchers/network_launcher.py
agentdock/launchers/terminal_console.py
agentdock/models/__init__.py
agentdock/models/manifest.py
agentdock/models/message_thread.py
agentdock/models/messages.py
agentdock/models/network_config.py
agentdock/models/network_profile.py
agentdock/models/tool.py
agentdock/protocols/__init__.py
agentdock/protocols/communication/__init__.py
agentdock/protocols/communication/simple_messaging/__init__.py
agentdock/protocols/communication/simple_messaging/adapter.py
agentdock/protocols/communication/simple_messaging/protocol.py
agentdock/protocols/discovery/__init__.py
agentdock/protocols/discovery/agent_discovery/__init__.py
agentdock/protocols/discovery/agent_discovery/adapter.py
agentdock/protocols/discovery/agent_discovery/protocol.py
agentdock/utils/__init__.py
agentdock/utils/message_util.py
agentdock/utils/network_discovey.py
agentdock/utils/protocol_loaders.py
agentdock-0.4.0.dist-info/licenses/LICENSE
agentdock-0.4.0.dist-info/METADATA
agentdock-0.4.0.dist-info/WHEEL
agentdock-0.4.0.dist-info/entry_points.txt
agentdock-0.4.0.dist-info/top_level.txt
agentdock-0.4.0.dist-info/RECORD
